AUTHORS
CHANGES
LICENSE
MANIFEST.in
README.rst
TODO
distribute_setup.py
requirements-cython.txt
requirements-setup.txt
requirements-sphinx.txt
requirements.py
requirements.txt
setup.cfg
setup.py
Soapbox.egg-info/PKG-INFO
Soapbox.egg-info/SOURCES.txt
Soapbox.egg-info/dependency_links.txt
Soapbox.egg-info/entry_points.txt
Soapbox.egg-info/not-zip-safe
Soapbox.egg-info/requires.txt
Soapbox.egg-info/top_level.txt
doc/Makefile
doc/make.bat
doc/source/Authors.rst
doc/source/Changes.rst
doc/source/Introduction.rst
doc/source/Issues.rst
doc/source/TODO.rst
doc/source/Tutorial.rst
doc/source/conf.py
doc/source/favicon.ico
doc/source/fds-icon.png
doc/source/index.rst
doc/source/modules.rst
doc/source/soapbox.rst
soapbox/__init__.py
soapbox/compat.py
soapbox/iso8601.py
soapbox/py2wsdl.py
soapbox/py2xsd.py
soapbox/settings.py
soapbox/soap.py
soapbox/soap11.py
soapbox/soap12.py
soapbox/utils.py
soapbox/wsdl.py
soapbox/wsdl2py.py
soapbox/xsd.py
soapbox/xsd2py.py
soapbox/xsdspec.py
soapbox/templates/__init__.py
soapbox/templates/__init__.pyc
soapbox/templates/wsdl
soapbox/templates/xsd