Metadata-Version: 1.0
Name: Soapbox
Version: 0.3.7
Summary: A SOAP library for Python.
Home-page: http://code.google.com/p/soapbox/
Author: Flight Data Services Ltd
Author-email: developers@flightdataservices.com
License: Open Software License (OSL-3.0)
Keywords: SOAP,WSDL,web service
Platform: OS Independent
Classifier: Development Status :: 4 - Beta
Classifier: Environment :: Console
Classifier: Environment :: Web Environment
Classifier: Framework :: Django
Classifier: Intended Audience :: Developers
Classifier: License :: OSI Approved
Classifier: Operating System :: OS Independent
Classifier: Programming Language :: Python :: 2.7
Classifier: Programming Language :: Python
Classifier: Topic :: Internet :: WWW/HTTP
Classifier: Topic :: Software Development :: Libraries :: Python Modules
